{
  "total_results": 20,
  "offers": [
    {
      "id": "rt_ss_257cb4b44546",
      "price": 410.74,
      "currency": "EUR",
      "price_formatted": "",
      "outbound": {
        "segments": [
          {
            "airline": "AD",
            "airline_name": "Azul Airlines",
            "flight_no": "AD6413",
            "origin": "POA",
            "destination": "CGH",
            "origin_city": "Porto Alegre",
            "destination_city": "Sao Paulo",
            "departure": "2026-04-30T07:05:00",
            "arrival": "2026-04-30T08:45:00",
            "duration_seconds": 6000,
            "cabin_class": "economy",
            "aircraft": ""
          },
          {
            "airline": "LA",
            "airline_name": "LATAM Airlines",
            "flight_no": "LA1300",
            "origin": "GRU",
            "destination": "ASU",
            "origin_city": "Sao Paulo",
            "destination_city": "Asuncion",
            "departure": "2026-05-01T08:20:00",
            "arrival": "2026-05-01T10:35:00",
            "duration_seconds": 8100,
            "cabin_class": "economy",
            "aircraft": ""
          }
        ],
        "total_duration_seconds": 99000,
        "stopovers": 1
      },
      "inbound": {
        "segments": [
          {
            "airline": "G3",
            "airline_name": "GOL Linhas A\u00e9reas",
            "flight_no": "G37481",
            "origin": "ASU",
            "destination": "GRU",
            "origin_city": "Asuncion",
            "destination_city": "Sao Paulo",
            "departure": "2026-05-03T12:05:00",
            "arrival": "2026-05-03T14:05:00",
            "duration_seconds": 7200,
            "cabin_class": "economy",
            "aircraft": ""
          },
          {
            "airline": "G3",
            "airline_name": "GOL Linhas A\u00e9reas",
            "flight_no": "G31236",
            "origin": "GRU",
            "destination": "POA",
            "origin_city": "Sao Paulo",
            "destination_city": "Porto Alegre",
            "departure": "2026-05-04T13:55:00",
            "arrival": "2026-05-04T15:40:00",
            "duration_seconds": 6300,
            "cabin_class": "economy",
            "aircraft": ""
          }
        ],
        "total_duration_seconds": 99300,
        "stopovers": 1
      },
      "airlines": [
        "AD",
        "LA",
        "G3"
      ],
      "owner_airline": "AD",
      "bags_price": {},
      "availability_seats": null,
      "conditions": {},
      "source": "skyscanner_meta",
      "source_tier": "free",
      "is_locked": false,
      "fetched_at": "2026-04-21T15:59:16.256267",
      "booking_url": "https://www.skyscanner.net/transport/flights/poa/asu/",
      "price_normalized": 410.74
    },
    {
      "id": "rt_ss_ef4f650de152",
      "price": 416.1,
      "currency": "EUR",
      "price_formatted": "",
      "outbound": {
        "segments": [
          {
            "airline": "G3",
            "airline_name": "GOL Linhas A\u00e9reas",
            "flight_no": "G31237",
            "origin": "POA",
            "destination": "GRU",
            "origin_city": "Porto Alegre",
            "destination_city": "Sao Paulo",
            "departure": "2026-04-30T13:20:00",
            "arrival": "2026-04-30T15:10:00",
            "duration_seconds": 6600,
            "cabin_class": "economy",
            "aircraft": ""
          },
          {
            "airline": "G3",
            "airline_name": "GOL Linhas A\u00e9reas",
            "flight_no": "G37480",
            "origin": "GRU",
            "destination": "ASU",
            "origin_city": "Sao Paulo",
            "destination_city": "Asuncion",
            "departure": "2026-05-01T09:00:00",
            "arrival": "2026-05-01T11:15:00",
            "duration_seconds": 8100,
            "cabin_class": "economy",
            "aircraft": ""
          }
        ],
        "total_duration_seconds": 78900,
        "stopovers": 1
      },
      "inbound": {
        "segments": [
          {
            "airline": "G3",
            "airline_name": "GOL Linhas A\u00e9reas",
            "flight_no": "G37481",
            "origin": "ASU",
            "destination": "GRU",
            "origin_city": "Asuncion",
            "destination_city": "Sao Paulo",
            "departure": "2026-05-03T12:05:00",
            "arrival": "2026-05-03T14:05:00",
            "duration_seconds": 7200,
            "cabin_class": "economy",
            "aircraft": ""
          },
          {
            "airline": "G3",
            "airline_name": "GOL Linhas A\u00e9reas",
            "flight_no": "G31236",
            "origin": "GRU",
            "destination": "POA",
            "origin_city": "Sao Paulo",
            "destination_city": "Porto Alegre",
            "departure": "2026-05-04T13:55:00",
            "arrival": "2026-05-04T15:40:00",
            "duration_seconds": 6300,
            "cabin_class": "economy",
            "aircraft": ""
          }
        ],
        "total_duration_seconds": 99300,
        "stopovers": 1
      },
      "airlines": [
        "G3"
      ],
      "owner_airline": "G3",
      "bags_price": {},
      "availability_seats": null,
      "conditions": {},
      "source": "skyscanner_meta",
      "source_tier": "free",
      "is_locked": false,
      "fetched_at": "2026-04-21T15:59:16.256267",
      "booking_url": "https://www.skyscanner.net/transport/flights/poa/asu/",
      "price_normalized": 416.1
    },
    {
      "id": "rt_ss_c85495a57fce",
      "price": 416.1,
      "currency": "EUR",
      "price_formatted": "",
      "outbound": {
        "segments": [
          {
            "airline": "G3",
            "airline_name": "GOL Linhas A\u00e9reas",
            "flight_no": "G31235",
            "origin": "POA",
            "destination": "GRU",
            "origin_city": "Porto Alegre",
            "destination_city": "Sao Paulo",
            "departure": "2026-04-30T11:35:00",
            "arrival": "2026-04-30T13:25:00",
            "duration_seconds": 6600,
            "cabin_class": "economy",
            "aircraft": ""
          },
          {
            "airline": "G3",
            "airline_name": "GOL Linhas A\u00e9reas",
            "flight_no": "G37480",
            "origin": "GRU",
            "destination": "ASU",
            "origin_city": "Sao Paulo",
            "destination_city": "Asuncion",
            "departure": "2026-05-01T09:00:00",
            "arrival": "2026-05-01T11:15:00",
            "duration_seconds": 8100,
            "cabin_class": "economy",
            "aircraft": ""
          }
        ],
        "total_duration_seconds": 85200,
        "stopovers": 1
      },
      "inbound": {
        "segments": [
          {
            "airline": "G3",
            "airline_name": "GOL Linhas A\u00e9reas",
            "flight_no": "G37481",
            "origin": "ASU",
            "destination": "GRU",
            "origin_city": "Asuncion",
            "destination_city": "Sao Paulo",
            "departure": "2026-05-03T12:05:00",
            "arrival": "2026-05-03T14:05:00",
            "duration_seconds": 7200,
            "cabin_class": "economy",
            "aircraft": ""
          },
          {
            "airline": "G3",
            "airline_name": "GOL Linhas A\u00e9reas",
            "flight_no": "G31236",
            "origin": "GRU",
            "destination": "POA",
            "origin_city": "Sao Paulo",
            "destination_city": "Porto Alegre",
            "departure": "2026-05-04T13:55:00",
            "arrival": "2026-05-04T15:40:00",
            "duration_seconds": 6300,
            "cabin_class": "economy",
            "aircraft": ""
          }
        ],
        "total_duration_seconds": 99300,
        "stopovers": 1
      },
      "airlines": [
        "G3"
      ],
      "owner_airline": "G3",
      "bags_price": {},
      "availability_seats": null,
      "conditions": {},
      "source": "skyscanner_meta",
      "source_tier": "free",
      "is_locked": false,
      "fetched_at": "2026-04-21T15:59:16.256267",
      "booking_url": "https://www.skyscanner.net/transport/flights/poa/asu/",
      "price_normalized": 416.1
    },
    {
      "id": "rt_ss_813ec7c49fae",
      "price": 416.49,
      "currency": "EUR",
      "price_formatted": "",
      "outbound": {
        "segments": [
          {
            "airline": "AD",
            "airline_name": "Azul Airlines",
            "flight_no": "AD6413",
            "origin": "POA",
            "destination": "CGH",
            "origin_city": "Porto Alegre",
            "destination_city": "Sao Paulo",
            "departure": "2026-04-30T07:05:00",
            "arrival": "2026-04-30T08:45:00",
            "duration_seconds": 6000,
            "cabin_class": "economy",
            "aircraft": ""
          },
          {
            "airline": "LA",
            "airline_name": "LATAM Airlines",
            "flight_no": "LA1300",
            "origin": "GRU",
            "destination": "ASU",
            "origin_city": "Sao Paulo",
            "destination_city": "Asuncion",
            "departure": "2026-05-01T08:20:00",
            "arrival": "2026-05-01T10:35:00",
            "duration_seconds": 8100,
            "cabin_class": "economy",
            "aircraft": ""
          }
        ],
        "total_duration_seconds": 99000,
        "stopovers": 1
      },
      "inbound": {
        "segments": [
          {
            "airline": "LA",
            "airline_name": "LATAM Airlines",
            "flight_no": "LA1305",
            "origin": "ASU",
            "destination": "GRU",
            "origin_city": "Asuncion",
            "destination_city": "Sao Paulo",
            "departure": "2026-05-03T13:15:00",
            "arrival": "2026-05-03T15:20:00",
            "duration_seconds": 7500,
            "cabin_class": "economy",
            "aircraft": ""
          },
          {
            "airline": "LA",
            "airline_name": "LATAM Airlines",
            "flight_no": "LA3422",
            "origin": "GRU",
            "destination": "POA",
            "origin_city": "Sao Paulo",
            "destination_city": "Porto Alegre",
            "departure": "2026-05-03T19:20:00",
            "arrival": "2026-05-03T21:05:00",
            "duration_seconds": 6300,
            "cabin_class": "economy",
            "aircraft": ""
          }
        ],
        "total_duration_seconds": 28200,
        "stopovers": 1
      },
      "airlines": [
        "AD",
        "LA"
      ],
      "owner_airline": "AD",
      "bags_price": {},
      "availability_seats": null,
      "conditions": {},
      "source": "skyscanner_meta",
      "source_tier": "free",
      "is_locked": false,
      "fetched_at": "2026-04-21T15:59:16.256267",
      "booking_url": "https://www.skyscanner.net/transport/flights/poa/asu/",
      "price_normalized": 416.49
    },
    {
      "id": "rt_ss_dd2fabbbbe30",
      "price": 421.85,
      "currency": "EUR",
      "price_formatted": "",
      "outbound": {
        "segments": [
          {
            "airline": "G3",
            "airline_name": "GOL Linhas A\u00e9reas",
            "flight_no": "G31237",
            "origin": "POA",
            "destination": "GRU",
            "origin_city": "Porto Alegre",
            "destination_city": "Sao Paulo",
            "departure": "2026-04-30T13:20:00",
            "arrival": "2026-04-30T15:10:00",
            "duration_seconds": 6600,
            "cabin_class": "economy",
            "aircraft": ""
          },
          {
            "airline": "G3",
            "airline_name": "GOL Linhas A\u00e9reas",
            "flight_no": "G37480",
            "origin": "GRU",
            "destination": "ASU",
            "origin_city": "Sao Paulo",
            "destination_city": "Asuncion",
            "departure": "2026-05-01T09:00:00",
            "arrival": "2026-05-01T11:15:00",
            "duration_seconds": 8100,
            "cabin_class": "economy",
            "aircraft": ""
          }
        ],
        "total_duration_seconds": 78900,
        "stopovers": 1
      },
      "inbound": {
        "segments": [
          {
            "airline": "LA",
            "airline_name": "LATAM Airlines",
            "flight_no": "LA1305",
            "origin": "ASU",
            "destination": "GRU",
            "origin_city": "Asuncion",
            "destination_city": "Sao Paulo",
            "departure": "2026-05-03T13:15:00",
            "arrival": "2026-05-03T15:20:00",
            "duration_seconds": 7500,
            "cabin_class": "economy",
            "aircraft": ""
          },
          {
            "airline": "LA",
            "airline_name": "LATAM Airlines",
            "flight_no": "LA3422",
            "origin": "GRU",
            "destination": "POA",
            "origin_city": "Sao Paulo",
            "destination_city": "Porto Alegre",
            "departure": "2026-05-03T19:20:00",
            "arrival": "2026-05-03T21:05:00",
            "duration_seconds": 6300,
            "cabin_class": "economy",
            "aircraft": ""
          }
        ],
        "total_duration_seconds": 28200,
        "stopovers": 1
      },
      "airlines": [
        "G3",
        "LA"
      ],
      "owner_airline": "G3",
      "bags_price": {},
      "availability_seats": null,
      "conditions": {},
      "source": "skyscanner_meta",
      "source_tier": "free",
      "is_locked": false,
      "fetched_at": "2026-04-21T15:59:16.256267",
      "booking_url": "https://www.skyscanner.net/transport/flights/poa/asu/",
      "price_normalized": 421.85
    },
    {
      "id": "rt_ss_6e2ecd5029ad",
      "price": 421.85,
      "currency": "EUR",
      "price_formatted": "",
      "outbound": {
        "segments": [
          {
            "airline": "G3",
            "airline_name": "GOL Linhas A\u00e9reas",
            "flight_no": "G31235",
            "origin": "POA",
            "destination": "GRU",
            "origin_city": "Porto Alegre",
            "destination_city": "Sao Paulo",
            "departure": "2026-04-30T11:35:00",
            "arrival": "2026-04-30T13:25:00",
            "duration_seconds": 6600,
            "cabin_class": "economy",
            "aircraft": ""
          },
          {
            "airline": "G3",
            "airline_name": "GOL Linhas A\u00e9reas",
            "flight_no": "G37480",
            "origin": "GRU",
            "destination": "ASU",
            "origin_city": "Sao Paulo",
            "destination_city": "Asuncion",
            "departure": "2026-05-01T09:00:00",
            "arrival": "2026-05-01T11:15:00",
            "duration_seconds": 8100,
            "cabin_class": "economy",
            "aircraft": ""
          }
        ],
        "total_duration_seconds": 85200,
        "stopovers": 1
      },
      "inbound": {
        "segments": [
          {
            "airline": "LA",
            "airline_name": "LATAM Airlines",
            "flight_no": "LA1305",
            "origin": "ASU",
            "destination": "GRU",
            "origin_city": "Asuncion",
            "destination_city": "Sao Paulo",
            "departure": "2026-05-03T13:15:00",
            "arrival": "2026-05-03T15:20:00",
            "duration_seconds": 7500,
            "cabin_class": "economy",
            "aircraft": ""
          },
          {
            "airline": "LA",
            "airline_name": "LATAM Airlines",
            "flight_no": "LA3422",
            "origin": "GRU",
            "destination": "POA",
            "origin_city": "Sao Paulo",
            "destination_city": "Porto Alegre",
            "departure": "2026-05-03T19:20:00",
            "arrival": "2026-05-03T21:05:00",
            "duration_seconds": 6300,
            "cabin_class": "economy",
            "aircraft": ""
          }
        ],
        "total_duration_seconds": 28200,
        "stopovers": 1
      },
      "airlines": [
        "G3",
        "LA"
      ],
      "owner_airline": "G3",
      "bags_price": {},
      "availability_seats": null,
      "conditions": {},
      "source": "skyscanner_meta",
      "source_tier": "free",
      "is_locked": false,
      "fetched_at": "2026-04-21T15:59:16.256267",
      "booking_url": "https://www.skyscanner.net/transport/flights/poa/asu/",
      "price_normalized": 421.85
    },
    {
      "id": "rt_ss_56ebfe18ba02",
      "price": 424.14,
      "currency": "EUR",
      "price_formatted": "",
      "outbound": {
        "segments": [
          {
            "airline": "LA",
            "airline_name": "LATAM Airlines",
            "flight_no": "LA3479",
            "origin": "POA",
            "destination": "GRU",
            "origin_city": "Porto Alegre",
            "destination_city": "Sao Paulo",
            "departure": "2026-04-30T04:45:00",
            "arrival": "2026-04-30T06:30:00",
            "duration_seconds": 6300,
            "cabin_class": "economy",
            "aircraft": ""
          },
          {
            "airline": "LA",
            "airline_name": "LATAM Airlines",
            "flight_no": "LA1300",
            "origin": "GRU",
            "destination": "ASU",
            "origin_city": "Sao Paulo",
            "destination_city": "Asuncion",
            "departure": "2026-04-30T07:55:00",
            "arrival": "2026-04-30T10:10:00",
            "duration_seconds": 8100,
            "cabin_class": "economy",
            "aircraft": ""
          }
        ],
        "total_duration_seconds": 19500,
        "stopovers": 1
      },
      "inbound": {
        "segments": [
          {
            "airline": "G3",
            "airline_name": "GOL Linhas A\u00e9reas",
            "flight_no": "G37481",
            "origin": "ASU",
            "destination": "GRU",
            "origin_city": "Asuncion",
            "destination_city": "Sao Paulo",
            "departure": "2026-05-03T12:05:00",
            "arrival": "2026-05-03T14:05:00",
            "duration_seconds": 7200,
            "cabin_class": "economy",
            "aircraft": ""
          },
          {
            "airline": "G3",
            "airline_name": "GOL Linhas A\u00e9reas",
            "flight_no": "G31236",
            "origin": "GRU",
            "destination": "POA",
            "origin_city": "Sao Paulo",
            "destination_city": "Porto Alegre",
            "departure": "2026-05-04T13:55:00",
            "arrival": "2026-05-04T15:40:00",
            "duration_seconds": 6300,
            "cabin_class": "economy",
            "aircraft": ""
          }
        ],
        "total_duration_seconds": 99300,
        "stopovers": 1
      },
      "airlines": [
        "LA",
        "G3"
      ],
      "owner_airline": "LA",
      "bags_price": {},
      "availability_seats": null,
      "conditions": {},
      "source": "skyscanner_meta",
      "source_tier": "free",
      "is_locked": false,
      "fetched_at": "2026-04-21T15:59:16.257262",
      "booking_url": "https://www.skyscanner.net/transport/flights/poa/asu/",
      "price_normalized": 424.14
    },
    {
      "id": "combo_c1c4664bd035",
      "price": 434.75,
      "currency": "EUR",
      "price_formatted": "434.75 EUR",
      "outbound": {
        "segments": [
          {
            "airline": "AD",
            "airline_name": "Azul",
            "flight_no": "AD6037",
            "origin": "POA",
            "destination": "CGH",
            "origin_city": "Porto Alegre",
            "destination_city": "S\u00e3o Paulo",
            "departure": "2026-04-30T09:00:00",
            "arrival": "2026-04-30T10:35:00",
            "duration_seconds": 5700,
            "cabin_class": "ECONOMY",
            "aircraft": ""
          },
          {
            "airline": "LA",
            "airline_name": "LATAM Airlines",
            "flight_no": "LA1300",
            "origin": "GRU",
            "destination": "ASU",
            "origin_city": "S\u00e3o Paulo",
            "destination_city": "Asunci\u00f3n",
            "departure": "2026-05-01T08:20:00",
            "arrival": "2026-05-01T10:35:00",
            "duration_seconds": 8100,
            "cabin_class": "ECONOMY",
            "aircraft": ""
          }
        ],
        "total_duration_seconds": 92100,
        "stopovers": 1
      },
      "inbound": {
        "segments": [
          {
            "airline": "G3",
            "airline_name": "GOL Linhas A\u00e9reas",
            "flight_no": "G37481",
            "origin": "ASU",
            "destination": "GRU",
            "origin_city": "Asuncion",
            "destination_city": "Sao Paulo",
            "departure": "2026-05-03T12:05:00",
            "arrival": "2026-05-03T14:05:00",
            "duration_seconds": 7200,
            "cabin_class": "economy",
            "aircraft": ""
          },
          {
            "airline": "G3",
            "airline_name": "GOL Linhas A\u00e9reas",
            "flight_no": "G31236",
            "origin": "GRU",
            "destination": "POA",
            "origin_city": "Sao Paulo",
            "destination_city": "Porto Alegre",
            "departure": "2026-05-04T13:55:00",
            "arrival": "2026-05-04T15:40:00",
            "duration_seconds": 6300,
            "cabin_class": "economy",
            "aircraft": ""
          }
        ],
        "total_duration_seconds": 99300,
        "stopovers": 1
      },
      "airlines": [
        "AD",
        "LA",
        "G3"
      ],
      "owner_airline": "AD|LA|G3",
      "bags_price": {},
      "availability_seats": null,
      "conditions": {
        "combo_type": "virtual_interlining",
        "outbound_booking_url": "https://www.kiwi.com/en/search/results/porto-alegre-state-of-rio-grande-do-sul-brazil/asuncion-paraguay/2026-04-30/no-return?sortBy=price",
        "inbound_booking_url": "https://www.skyscanner.net/transport/flights/asu/poa/",
        "outbound_source": "kiwi_connector",
        "inbound_source": "skyscanner_meta"
      },
      "source": "combo:kiwi_connector+skyscanner_meta",
      "source_tier": "free",
      "is_locked": false,
      "fetched_at": "2026-04-21T16:00:59.122220",
      "booking_url": "",
      "price_normalized": 434.75
    },
    {
      "id": "combo_bc02d81fe19a",
      "price": 440.5,
      "currency": "EUR",
      "price_formatted": "440.50 EUR",
      "outbound": {
        "segments": [
          {
            "airline": "AD",
            "airline_name": "Azul",
            "flight_no": "AD6037",
            "origin": "POA",
            "destination": "CGH",
            "origin_city": "Porto Alegre",
            "destination_city": "S\u00e3o Paulo",
            "departure": "2026-04-30T09:00:00",
            "arrival": "2026-04-30T10:35:00",
            "duration_seconds": 5700,
            "cabin_class": "ECONOMY",
            "aircraft": ""
          },
          {
            "airline": "LA",
            "airline_name": "LATAM Airlines",
            "flight_no": "LA1300",
            "origin": "GRU",
            "destination": "ASU",
            "origin_city": "S\u00e3o Paulo",
            "destination_city": "Asunci\u00f3n",
            "departure": "2026-05-01T08:20:00",
            "arrival": "2026-05-01T10:35:00",
            "duration_seconds": 8100,
            "cabin_class": "ECONOMY",
            "aircraft": ""
          }
        ],
        "total_duration_seconds": 92100,
        "stopovers": 1
      },
      "inbound": {
        "segments": [
          {
            "airline": "LA",
            "airline_name": "LATAM Airlines",
            "flight_no": "LA1305",
            "origin": "ASU",
            "destination": "GRU",
            "origin_city": "Asuncion",
            "destination_city": "Sao Paulo",
            "departure": "2026-05-03T13:15:00",
            "arrival": "2026-05-03T15:20:00",
            "duration_seconds": 7500,
            "cabin_class": "economy",
            "aircraft": ""
          },
          {
            "airline": "LA",
            "airline_name": "LATAM Airlines",
            "flight_no": "LA3422",
            "origin": "GRU",
            "destination": "POA",
            "origin_city": "Sao Paulo",
            "destination_city": "Porto Alegre",
            "departure": "2026-05-03T19:20:00",
            "arrival": "2026-05-03T21:05:00",
            "duration_seconds": 6300,
            "cabin_class": "economy",
            "aircraft": ""
          }
        ],
        "total_duration_seconds": 28200,
        "stopovers": 1
      },
      "airlines": [
        "AD",
        "LA"
      ],
      "owner_airline": "AD|LA",
      "bags_price": {},
      "availability_seats": null,
      "conditions": {
        "combo_type": "virtual_interlining",
        "outbound_booking_url": "https://www.kiwi.com/en/search/results/porto-alegre-state-of-rio-grande-do-sul-brazil/asuncion-paraguay/2026-04-30/no-return?sortBy=price",
        "inbound_booking_url": "https://www.skyscanner.net/transport/flights/asu/poa/",
        "outbound_source": "kiwi_connector",
        "inbound_source": "skyscanner_meta"
      },
      "source": "combo:kiwi_connector+skyscanner_meta",
      "source_tier": "free",
      "is_locked": false,
      "fetched_at": "2026-04-21T16:00:59.122220",
      "booking_url": "",
      "price_normalized": 440.5
    },
    {
      "id": "combo_98aa5c81820f",
      "price": 445.75,
      "currency": "EUR",
      "price_formatted": "445.75 EUR",
      "outbound": {
        "segments": [
          {
            "airline": "G3",
            "airline_name": "Gol Transportes A\u00e9reos",
            "flight_no": "G31237",
            "origin": "POA",
            "destination": "GRU",
            "origin_city": "Porto Alegre",
            "destination_city": "S\u00e3o Paulo",
            "departure": "2026-04-30T13:20:00",
            "arrival": "2026-04-30T15:10:00",
            "duration_seconds": 6600,
            "cabin_class": "ECONOMY",
            "aircraft": ""
          },
          {
            "airline": "LA",
            "airline_name": "LATAM Airlines",
            "flight_no": "LA1300",
            "origin": "GRU",
            "destination": "ASU",
            "origin_city": "S\u00e3o Paulo",
            "destination_city": "Asunci\u00f3n",
            "departure": "2026-05-01T08:20:00",
            "arrival": "2026-05-01T10:35:00",
            "duration_seconds": 8100,
            "cabin_class": "ECONOMY",
            "aircraft": ""
          }
        ],
        "total_duration_seconds": 76500,
        "stopovers": 1
      },
      "inbound": {
        "segments": [
          {
            "airline": "G3",
            "airline_name": "GOL Linhas A\u00e9reas",
            "flight_no": "G37481",
            "origin": "ASU",
            "destination": "GRU",
            "origin_city": "Asuncion",
            "destination_city": "Sao Paulo",
            "departure": "2026-05-03T12:05:00",
            "arrival": "2026-05-03T14:05:00",
            "duration_seconds": 7200,
            "cabin_class": "economy",
            "aircraft": ""
          },
          {
            "airline": "G3",
            "airline_name": "GOL Linhas A\u00e9reas",
            "flight_no": "G31236",
            "origin": "GRU",
            "destination": "POA",
            "origin_city": "Sao Paulo",
            "destination_city": "Porto Alegre",
            "departure": "2026-05-04T13:55:00",
            "arrival": "2026-05-04T15:40:00",
            "duration_seconds": 6300,
            "cabin_class": "economy",
            "aircraft": ""
          }
        ],
        "total_duration_seconds": 99300,
        "stopovers": 1
      },
      "airlines": [
        "G3",
        "LA"
      ],
      "owner_airline": "G3|LA",
      "bags_price": {},
      "availability_seats": null,
      "conditions": {
        "combo_type": "virtual_interlining",
        "outbound_booking_url": "https://www.kiwi.com/en/search/results/porto-alegre-state-of-rio-grande-do-sul-brazil/asuncion-paraguay/2026-04-30/no-return?sortBy=price",
        "inbound_booking_url": "https://www.skyscanner.net/transport/flights/asu/poa/",
        "outbound_source": "kiwi_connector",
        "inbound_source": "skyscanner_meta"
      },
      "source": "combo:kiwi_connector+skyscanner_meta",
      "source_tier": "free",
      "is_locked": false,
      "fetched_at": "2026-04-21T16:00:59.122220",
      "booking_url": "",
      "price_normalized": 445.75
    },
    {
      "id": "combo_7f9acee48d53",
      "price": 457.84,
      "currency": "EUR",
      "price_formatted": "457.84 EUR",
      "outbound": {
        "segments": [
          {
            "airline": "LA",
            "airline_name": "LATAM Airlines",
            "flight_no": "LA3479",
            "origin": "POA",
            "destination": "GRU",
            "origin_city": "Porto Alegre",
            "destination_city": "S\u00e3o Paulo",
            "departure": "2026-04-30T04:45:00",
            "arrival": "2026-04-30T06:30:00",
            "duration_seconds": 6300,
            "cabin_class": "ECONOMY",
            "aircraft": ""
          },
          {
            "airline": "LA",
            "airline_name": "LATAM Airlines",
            "flight_no": "LA1300",
            "origin": "GRU",
            "destination": "ASU",
            "origin_city": "S\u00e3o Paulo",
            "destination_city": "Asunci\u00f3n",
            "departure": "2026-04-30T07:55:00",
            "arrival": "2026-04-30T10:10:00",
            "duration_seconds": 8100,
            "cabin_class": "ECONOMY",
            "aircraft": ""
          }
        ],
        "total_duration_seconds": 19500,
        "stopovers": 1
      },
      "inbound": {
        "segments": [
          {
            "airline": "G3",
            "airline_name": "GOL Linhas A\u00e9reas",
            "flight_no": "G37759",
            "origin": "ASU",
            "destination": "GIG",
            "origin_city": "Asuncion",
            "destination_city": "Rio de Janeiro",
            "departure": "2026-05-03T03:35:00",
            "arrival": "2026-05-03T06:00:00",
            "duration_seconds": 8700,
            "cabin_class": "economy",
            "aircraft": ""
          },
          {
            "airline": "G3",
            "airline_name": "GOL Linhas A\u00e9reas",
            "flight_no": "G39338",
            "origin": "GIG",
            "destination": "FLN",
            "origin_city": "Rio de Janeiro",
            "destination_city": "Florianopolis",
            "departure": "2026-05-04T02:00:00",
            "arrival": "2026-05-04T03:40:00",
            "duration_seconds": 6000,
            "cabin_class": "economy",
            "aircraft": ""
          },
          {
            "airline": "G3",
            "airline_name": "GOL Linhas A\u00e9reas",
            "flight_no": "G32104",
            "origin": "FLN",
            "destination": "POA",
            "origin_city": "Florianopolis",
            "destination_city": "Porto Alegre",
            "departure": "2026-05-04T21:40:00",
            "arrival": "2026-05-04T22:45:00",
            "duration_seconds": 3900,
            "cabin_class": "economy",
            "aircraft": ""
          }
        ],
        "total_duration_seconds": 155400,
        "stopovers": 2
      },
      "airlines": [
        "LA",
        "G3"
      ],
      "owner_airline": "LA|G3",
      "bags_price": {},
      "availability_seats": null,
      "conditions": {
        "combo_type": "virtual_interlining",
        "outbound_booking_url": "https://www.kiwi.com/en/search/results/porto-alegre-state-of-rio-grande-do-sul-brazil/asuncion-paraguay/2026-04-30/no-return?sortBy=price",
        "inbound_booking_url": "https://www.skyscanner.net/transport/flights/asu/poa/",
        "outbound_source": "kiwi_connector",
        "inbound_source": "skyscanner_meta"
      },
      "source": "combo:kiwi_connector+skyscanner_meta",
      "source_tier": "free",
      "is_locked": false,
      "fetched_at": "2026-04-21T16:00:59.122220",
      "booking_url": "",
      "price_normalized": 457.84
    },
    {
      "id": "rt_mm_fd2430ba53db",
      "price": 491.0,
      "currency": "USD",
      "price_formatted": "",
      "outbound": {
        "segments": [
          {
            "airline": "G3",
            "airline_name": "GOL",
            "flight_no": "G32105",
            "origin": "POA",
            "destination": "FLN",
            "origin_city": "",
            "destination_city": "",
            "departure": "2026-04-30T06:00:00",
            "arrival": "2026-04-30T07:05:00",
            "duration_seconds": 0,
            "cabin_class": "economy",
            "aircraft": ""
          },
          {
            "airline": "G3",
            "airline_name": "GOL",
            "flight_no": "G31143",
            "origin": "FLN",
            "destination": "GRU",
            "origin_city": "",
            "destination_city": "",
            "departure": "2026-04-30T19:05:00",
            "arrival": "2026-04-30T20:40:00",
            "duration_seconds": 0,
            "cabin_class": "economy",
            "aircraft": ""
          },
          {
            "airline": "G3",
            "airline_name": "GOL",
            "flight_no": "G37480",
            "origin": "GRU",
            "destination": "ASU",
            "origin_city": "",
            "destination_city": "",
            "departure": "2026-05-01T09:00:00",
            "arrival": "2026-05-01T11:15:00",
            "duration_seconds": 0,
            "cabin_class": "economy",
            "aircraft": ""
          }
        ],
        "total_duration_seconds": 105300,
        "stopovers": 2
      },
      "inbound": {
        "segments": [
          {
            "airline": "G3",
            "airline_name": "GOL",
            "flight_no": "G37481",
            "origin": "ASU",
            "destination": "GRU",
            "origin_city": "",
            "destination_city": "",
            "departure": "2026-05-03T12:05:00",
            "arrival": "2026-05-03T14:05:00",
            "duration_seconds": 0,
            "cabin_class": "economy",
            "aircraft": ""
          },
          {
            "airline": "G3",
            "airline_name": "GOL",
            "flight_no": "G31140",
            "origin": "GRU",
            "destination": "FLN",
            "origin_city": "",
            "destination_city": "",
            "departure": "2026-05-04T09:15:00",
            "arrival": "2026-05-04T10:35:00",
            "duration_seconds": 0,
            "cabin_class": "economy",
            "aircraft": ""
          },
          {
            "airline": "G3",
            "airline_name": "GOL",
            "flight_no": "G32104",
            "origin": "FLN",
            "destination": "POA",
            "origin_city": "",
            "destination_city": "",
            "departure": "2026-05-04T21:40:00",
            "arrival": "2026-05-04T22:45:00",
            "duration_seconds": 0,
            "cabin_class": "economy",
            "aircraft": ""
          }
        ],
        "total_duration_seconds": 124800,
        "stopovers": 2
      },
      "airlines": [
        "G3"
      ],
      "owner_airline": "G3",
      "bags_price": {},
      "availability_seats": null,
      "conditions": {},
      "source": "momondo_meta",
      "source_tier": "free",
      "is_locked": false,
      "fetched_at": "2026-04-21T15:58:55.732593",
      "booking_url": "https://www.momondo.com/flight-search/POA-ASU/2026-04-30",
      "price_normalized": 417.26653
    },
    {
      "id": "rt_mm_6153b7972fb3",
      "price": 503.0,
      "currency": "USD",
      "price_formatted": "",
      "outbound": {
        "segments": [
          {
            "airline": "LA",
            "airline_name": "LATAM Airlines",
            "flight_no": "LA3403",
            "origin": "POA",
            "destination": "GRU",
            "origin_city": "",
            "destination_city": "",
            "departure": "2026-04-30T22:50:00",
            "arrival": "2026-05-01T00:35:00",
            "duration_seconds": 0,
            "cabin_class": "economy",
            "aircraft": ""
          },
          {
            "airline": "LA",
            "airline_name": "LATAM Airlines",
            "flight_no": "LA1300",
            "origin": "GRU",
            "destination": "ASU",
            "origin_city": "",
            "destination_city": "",
            "departure": "2026-05-01T08:20:00",
            "arrival": "2026-05-01T10:35:00",
            "duration_seconds": 0,
            "cabin_class": "economy",
            "aircraft": ""
          }
        ],
        "total_duration_seconds": 42300,
        "stopovers": 1
      },
      "inbound": {
        "segments": [
          {
            "airline": "G3",
            "airline_name": "GOL",
            "flight_no": "G37481",
            "origin": "ASU",
            "destination": "GRU",
            "origin_city": "",
            "destination_city": "",
            "departure": "2026-05-03T12:05:00",
            "arrival": "2026-05-03T14:05:00",
            "duration_seconds": 0,
            "cabin_class": "economy",
            "aircraft": ""
          },
          {
            "airline": "G3",
            "airline_name": "GOL",
            "flight_no": "G31140",
            "origin": "GRU",
            "destination": "FLN",
            "origin_city": "",
            "destination_city": "",
            "departure": "2026-05-04T09:15:00",
            "arrival": "2026-05-04T10:35:00",
            "duration_seconds": 0,
            "cabin_class": "economy",
            "aircraft": ""
          },
          {
            "airline": "G3",
            "airline_name": "GOL",
            "flight_no": "G32104",
            "origin": "FLN",
            "destination": "POA",
            "origin_city": "",
            "destination_city": "",
            "departure": "2026-05-04T21:40:00",
            "arrival": "2026-05-04T22:45:00",
            "duration_seconds": 0,
            "cabin_class": "economy",
            "aircraft": ""
          }
        ],
        "total_duration_seconds": 124800,
        "stopovers": 2
      },
      "airlines": [
        "LA",
        "G3"
      ],
      "owner_airline": "LA",
      "bags_price": {},
      "availability_seats": null,
      "conditions": {},
      "source": "momondo_meta",
      "source_tier": "free",
      "is_locked": false,
      "fetched_at": "2026-04-21T15:58:55.732593",
      "booking_url": "https://www.momondo.com/flight-search/POA-ASU/2026-04-30",
      "price_normalized": 427.46449
    },
    {
      "id": "rt_mm_392bb834ee51",
      "price": 503.0,
      "currency": "USD",
      "price_formatted": "",
      "outbound": {
        "segments": [
          {
            "airline": "LA",
            "airline_name": "LATAM Airlines",
            "flight_no": "LA3551",
            "origin": "POA",
            "destination": "GRU",
            "origin_city": "",
            "destination_city": "",
            "departure": "2026-04-30T21:00:00",
            "arrival": "2026-04-30T22:45:00",
            "duration_seconds": 0,
            "cabin_class": "economy",
            "aircraft": ""
          },
          {
            "airline": "LA",
            "airline_name": "LATAM Airlines",
            "flight_no": "LA1300",
            "origin": "GRU",
            "destination": "ASU",
            "origin_city": "",
            "destination_city": "",
            "departure": "2026-05-01T08:20:00",
            "arrival": "2026-05-01T10:35:00",
            "duration_seconds": 0,
            "cabin_class": "economy",
            "aircraft": ""
          }
        ],
        "total_duration_seconds": 48900,
        "stopovers": 1
      },
      "inbound": {
        "segments": [
          {
            "airline": "G3",
            "airline_name": "GOL",
            "flight_no": "G37481",
            "origin": "ASU",
            "destination": "GRU",
            "origin_city": "",
            "destination_city": "",
            "departure": "2026-05-03T12:05:00",
            "arrival": "2026-05-03T14:05:00",
            "duration_seconds": 0,
            "cabin_class": "economy",
            "aircraft": ""
          },
          {
            "airline": "G3",
            "airline_name": "GOL",
            "flight_no": "G31140",
            "origin": "GRU",
            "destination": "FLN",
            "origin_city": "",
            "destination_city": "",
            "departure": "2026-05-04T09:15:00",
            "arrival": "2026-05-04T10:35:00",
            "duration_seconds": 0,
            "cabin_class": "economy",
            "aircraft": ""
          },
          {
            "airline": "G3",
            "airline_name": "GOL",
            "flight_no": "G32104",
            "origin": "FLN",
            "destination": "POA",
            "origin_city": "",
            "destination_city": "",
            "departure": "2026-05-04T21:40:00",
            "arrival": "2026-05-04T22:45:00",
            "duration_seconds": 0,
            "cabin_class": "economy",
            "aircraft": ""
          }
        ],
        "total_duration_seconds": 124800,
        "stopovers": 2
      },
      "airlines": [
        "LA",
        "G3"
      ],
      "owner_airline": "LA",
      "bags_price": {},
      "availability_seats": null,
      "conditions": {},
      "source": "momondo_meta",
      "source_tier": "free",
      "is_locked": false,
      "fetched_at": "2026-04-21T15:58:55.732593",
      "booking_url": "https://www.momondo.com/flight-search/POA-ASU/2026-04-30",
      "price_normalized": 427.46449
    },
    {
      "id": "rt_mm_9ba9595acd25",
      "price": 503.0,
      "currency": "USD",
      "price_formatted": "",
      "outbound": {
        "segments": [
          {
            "airline": "G3",
            "airline_name": "GOL",
            "flight_no": "G32105",
            "origin": "POA",
            "destination": "FLN",
            "origin_city": "",
            "destination_city": "",
            "departure": "2026-04-30T06:00:00",
            "arrival": "2026-04-30T07:05:00",
            "duration_seconds": 0,
            "cabin_class": "economy",
            "aircraft": ""
          },
          {
            "airline": "G3",
            "airline_name": "GOL",
            "flight_no": "G31143",
            "origin": "FLN",
            "destination": "GRU",
            "origin_city": "",
            "destination_city": "",
            "departure": "2026-04-30T19:05:00",
            "arrival": "2026-04-30T20:40:00",
            "duration_seconds": 0,
            "cabin_class": "economy",
            "aircraft": ""
          },
          {
            "airline": "G3",
            "airline_name": "GOL",
            "flight_no": "G37480",
            "origin": "GRU",
            "destination": "ASU",
            "origin_city": "",
            "destination_city": "",
            "departure": "2026-05-01T09:00:00",
            "arrival": "2026-05-01T11:15:00",
            "duration_seconds": 0,
            "cabin_class": "economy",
            "aircraft": ""
          }
        ],
        "total_duration_seconds": 105300,
        "stopovers": 2
      },
      "inbound": {
        "segments": [
          {
            "airline": "LA",
            "airline_name": "LATAM Airlines",
            "flight_no": "LA1305",
            "origin": "ASU",
            "destination": "GRU",
            "origin_city": "",
            "destination_city": "",
            "departure": "2026-05-03T13:15:00",
            "arrival": "2026-05-03T15:20:00",
            "duration_seconds": 0,
            "cabin_class": "economy",
            "aircraft": ""
          },
          {
            "airline": "LA",
            "airline_name": "LATAM Airlines",
            "flight_no": "LA3422",
            "origin": "GRU",
            "destination": "POA",
            "origin_city": "",
            "destination_city": "",
            "departure": "2026-05-03T19:20:00",
            "arrival": "2026-05-03T21:05:00",
            "duration_seconds": 0,
            "cabin_class": "economy",
            "aircraft": ""
          }
        ],
        "total_duration_seconds": 28200,
        "stopovers": 1
      },
      "airlines": [
        "G3",
        "LA"
      ],
      "owner_airline": "G3",
      "bags_price": {},
      "availability_seats": null,
      "conditions": {},
      "source": "momondo_meta",
      "source_tier": "free",
      "is_locked": false,
      "fetched_at": "2026-04-21T15:58:55.732593",
      "booking_url": "https://www.momondo.com/flight-search/POA-ASU/2026-04-30",
      "price_normalized": 427.46449
    },
    {
      "id": "rt_mm_657b5315cc5a",
      "price": 504.0,
      "currency": "USD",
      "price_formatted": "",
      "outbound": {
        "segments": [
          {
            "airline": "LA",
            "airline_name": "LATAM Airlines",
            "flight_no": "LA3159",
            "origin": "POA",
            "destination": "CGH",
            "origin_city": "",
            "destination_city": "",
            "departure": "2026-04-30T12:20:00",
            "arrival": "2026-04-30T13:55:00",
            "duration_seconds": 0,
            "cabin_class": "economy",
            "aircraft": ""
          },
          {
            "airline": "LA",
            "airline_name": "LATAM Airlines",
            "flight_no": "LA1302",
            "origin": "GRU",
            "destination": "ASU",
            "origin_city": "",
            "destination_city": "",
            "departure": "2026-04-30T21:40:00",
            "arrival": "2026-04-30T23:55:00",
            "duration_seconds": 0,
            "cabin_class": "economy",
            "aircraft": ""
          }
        ],
        "total_duration_seconds": 41700,
        "stopovers": 1
      },
      "inbound": {
        "segments": [
          {
            "airline": "G3",
            "airline_name": "GOL",
            "flight_no": "G37481",
            "origin": "ASU",
            "destination": "GRU",
            "origin_city": "",
            "destination_city": "",
            "departure": "2026-05-03T12:05:00",
            "arrival": "2026-05-03T14:05:00",
            "duration_seconds": 0,
            "cabin_class": "economy",
            "aircraft": ""
          },
          {
            "airline": "G3",
            "airline_name": "GOL",
            "flight_no": "G31140",
            "origin": "GRU",
            "destination": "FLN",
            "origin_city": "",
            "destination_city": "",
            "departure": "2026-05-04T09:15:00",
            "arrival": "2026-05-04T10:35:00",
            "duration_seconds": 0,
            "cabin_class": "economy",
            "aircraft": ""
          },
          {
            "airline": "G3",
            "airline_name": "GOL",
            "flight_no": "G32104",
            "origin": "FLN",
            "destination": "POA",
            "origin_city": "",
            "destination_city": "",
            "departure": "2026-05-04T21:40:00",
            "arrival": "2026-05-04T22:45:00",
            "duration_seconds": 0,
            "cabin_class": "economy",
            "aircraft": ""
          }
        ],
        "total_duration_seconds": 124800,
        "stopovers": 2
      },
      "airlines": [
        "LA",
        "G3"
      ],
      "owner_airline": "LA",
      "bags_price": {},
      "availability_seats": null,
      "conditions": {},
      "source": "momondo_meta",
      "source_tier": "free",
      "is_locked": false,
      "fetched_at": "2026-04-21T15:58:55.732593",
      "booking_url": "https://www.momondo.com/flight-search/POA-ASU/2026-04-30",
      "price_normalized": 428.31432
    },
    {
      "id": "rt_mm_1cf619a58faf",
      "price": 504.0,
      "currency": "USD",
      "price_formatted": "",
      "outbound": {
        "segments": [
          {
            "airline": "LA",
            "airline_name": "LATAM Airlines",
            "flight_no": "LA3155",
            "origin": "POA",
            "destination": "CGH",
            "origin_city": "",
            "destination_city": "",
            "departure": "2026-04-30T10:00:00",
            "arrival": "2026-04-30T11:35:00",
            "duration_seconds": 0,
            "cabin_class": "economy",
            "aircraft": ""
          },
          {
            "airline": "LA",
            "airline_name": "LATAM Airlines",
            "flight_no": "LA1302",
            "origin": "GRU",
            "destination": "ASU",
            "origin_city": "",
            "destination_city": "",
            "departure": "2026-04-30T21:40:00",
            "arrival": "2026-04-30T23:55:00",
            "duration_seconds": 0,
            "cabin_class": "economy",
            "aircraft": ""
          }
        ],
        "total_duration_seconds": 50100,
        "stopovers": 1
      },
      "inbound": {
        "segments": [
          {
            "airline": "G3",
            "airline_name": "GOL",
            "flight_no": "G37481",
            "origin": "ASU",
            "destination": "GRU",
            "origin_city": "",
            "destination_city": "",
            "departure": "2026-05-03T12:05:00",
            "arrival": "2026-05-03T14:05:00",
            "duration_seconds": 0,
            "cabin_class": "economy",
            "aircraft": ""
          },
          {
            "airline": "G3",
            "airline_name": "GOL",
            "flight_no": "G31140",
            "origin": "GRU",
            "destination": "FLN",
            "origin_city": "",
            "destination_city": "",
            "departure": "2026-05-04T09:15:00",
            "arrival": "2026-05-04T10:35:00",
            "duration_seconds": 0,
            "cabin_class": "economy",
            "aircraft": ""
          },
          {
            "airline": "G3",
            "airline_name": "GOL",
            "flight_no": "G32104",
            "origin": "FLN",
            "destination": "POA",
            "origin_city": "",
            "destination_city": "",
            "departure": "2026-05-04T21:40:00",
            "arrival": "2026-05-04T22:45:00",
            "duration_seconds": 0,
            "cabin_class": "economy",
            "aircraft": ""
          }
        ],
        "total_duration_seconds": 124800,
        "stopovers": 2
      },
      "airlines": [
        "LA",
        "G3"
      ],
      "owner_airline": "LA",
      "bags_price": {},
      "availability_seats": null,
      "conditions": {},
      "source": "momondo_meta",
      "source_tier": "free",
      "is_locked": false,
      "fetched_at": "2026-04-21T15:58:55.732593",
      "booking_url": "https://www.momondo.com/flight-search/POA-ASU/2026-04-30",
      "price_normalized": 428.31432
    },
    {
      "id": "rt_mm_afc59b94682a",
      "price": 504.0,
      "currency": "USD",
      "price_formatted": "",
      "outbound": {
        "segments": [
          {
            "airline": "LA",
            "airline_name": "LATAM Airlines",
            "flight_no": "LA3153",
            "origin": "POA",
            "destination": "CGH",
            "origin_city": "",
            "destination_city": "",
            "departure": "2026-04-30T08:50:00",
            "arrival": "2026-04-30T10:25:00",
            "duration_seconds": 0,
            "cabin_class": "economy",
            "aircraft": ""
          },
          {
            "airline": "LA",
            "airline_name": "LATAM Airlines",
            "flight_no": "LA1302",
            "origin": "GRU",
            "destination": "ASU",
            "origin_city": "",
            "destination_city": "",
            "departure": "2026-04-30T21:40:00",
            "arrival": "2026-04-30T23:55:00",
            "duration_seconds": 0,
            "cabin_class": "economy",
            "aircraft": ""
          }
        ],
        "total_duration_seconds": 54300,
        "stopovers": 1
      },
      "inbound": {
        "segments": [
          {
            "airline": "G3",
            "airline_name": "GOL",
            "flight_no": "G37481",
            "origin": "ASU",
            "destination": "GRU",
            "origin_city": "",
            "destination_city": "",
            "departure": "2026-05-03T12:05:00",
            "arrival": "2026-05-03T14:05:00",
            "duration_seconds": 0,
            "cabin_class": "economy",
            "aircraft": ""
          },
          {
            "airline": "G3",
            "airline_name": "GOL",
            "flight_no": "G31140",
            "origin": "GRU",
            "destination": "FLN",
            "origin_city": "",
            "destination_city": "",
            "departure": "2026-05-04T09:15:00",
            "arrival": "2026-05-04T10:35:00",
            "duration_seconds": 0,
            "cabin_class": "economy",
            "aircraft": ""
          },
          {
            "airline": "G3",
            "airline_name": "GOL",
            "flight_no": "G32104",
            "origin": "FLN",
            "destination": "POA",
            "origin_city": "",
            "destination_city": "",
            "departure": "2026-05-04T21:40:00",
            "arrival": "2026-05-04T22:45:00",
            "duration_seconds": 0,
            "cabin_class": "economy",
            "aircraft": ""
          }
        ],
        "total_duration_seconds": 124800,
        "stopovers": 2
      },
      "airlines": [
        "LA",
        "G3"
      ],
      "owner_airline": "LA",
      "bags_price": {},
      "availability_seats": null,
      "conditions": {},
      "source": "momondo_meta",
      "source_tier": "free",
      "is_locked": false,
      "fetched_at": "2026-04-21T15:58:55.732593",
      "booking_url": "https://www.momondo.com/flight-search/POA-ASU/2026-04-30",
      "price_normalized": 428.31432
    },
    {
      "id": "rt_mm_dd1b7828f304",
      "price": 504.0,
      "currency": "USD",
      "price_formatted": "",
      "outbound": {
        "segments": [
          {
            "airline": "LA",
            "airline_name": "LATAM Airlines",
            "flight_no": "LA3415",
            "origin": "POA",
            "destination": "GRU",
            "origin_city": "",
            "destination_city": "",
            "departure": "2026-04-30T06:45:00",
            "arrival": "2026-04-30T08:30:00",
            "duration_seconds": 0,
            "cabin_class": "economy",
            "aircraft": ""
          },
          {
            "airline": "LA",
            "airline_name": "LATAM Airlines",
            "flight_no": "LA1302",
            "origin": "GRU",
            "destination": "ASU",
            "origin_city": "",
            "destination_city": "",
            "departure": "2026-04-30T21:40:00",
            "arrival": "2026-04-30T23:55:00",
            "duration_seconds": 0,
            "cabin_class": "economy",
            "aircraft": ""
          }
        ],
        "total_duration_seconds": 61800,
        "stopovers": 1
      },
      "inbound": {
        "segments": [
          {
            "airline": "G3",
            "airline_name": "GOL",
            "flight_no": "G37481",
            "origin": "ASU",
            "destination": "GRU",
            "origin_city": "",
            "destination_city": "",
            "departure": "2026-05-03T12:05:00",
            "arrival": "2026-05-03T14:05:00",
            "duration_seconds": 0,
            "cabin_class": "economy",
            "aircraft": ""
          },
          {
            "airline": "G3",
            "airline_name": "GOL",
            "flight_no": "G31140",
            "origin": "GRU",
            "destination": "FLN",
            "origin_city": "",
            "destination_city": "",
            "departure": "2026-05-04T09:15:00",
            "arrival": "2026-05-04T10:35:00",
            "duration_seconds": 0,
            "cabin_class": "economy",
            "aircraft": ""
          },
          {
            "airline": "G3",
            "airline_name": "GOL",
            "flight_no": "G32104",
            "origin": "FLN",
            "destination": "POA",
            "origin_city": "",
            "destination_city": "",
            "departure": "2026-05-04T21:40:00",
            "arrival": "2026-05-04T22:45:00",
            "duration_seconds": 0,
            "cabin_class": "economy",
            "aircraft": ""
          }
        ],
        "total_duration_seconds": 124800,
        "stopovers": 2
      },
      "airlines": [
        "LA",
        "G3"
      ],
      "owner_airline": "LA",
      "bags_price": {},
      "availability_seats": null,
      "conditions": {},
      "source": "momondo_meta",
      "source_tier": "free",
      "is_locked": false,
      "fetched_at": "2026-04-21T15:58:55.732593",
      "booking_url": "https://www.momondo.com/flight-search/POA-ASU/2026-04-30",
      "price_normalized": 428.31432
    },
    {
      "id": "rt_mm_99ce25dcc54f",
      "price": 506.0,
      "currency": "USD",
      "price_formatted": "",
      "outbound": {
        "segments": [
          {
            "airline": "G3",
            "airline_name": "GOL",
            "flight_no": "G31239",
            "origin": "POA",
            "destination": "GRU",
            "origin_city": "",
            "destination_city": "",
            "departure": "2026-04-30T18:15:00",
            "arrival": "2026-04-30T20:15:00",
            "duration_seconds": 0,
            "cabin_class": "economy",
            "aircraft": ""
          },
          {
            "airline": "G3",
            "airline_name": "GOL",
            "flight_no": "G37480",
            "origin": "GRU",
            "destination": "ASU",
            "origin_city": "",
            "destination_city": "",
            "departure": "2026-05-01T09:00:00",
            "arrival": "2026-05-01T11:15:00",
            "duration_seconds": 0,
            "cabin_class": "economy",
            "aircraft": ""
          }
        ],
        "total_duration_seconds": 61200,
        "stopovers": 1
      },
      "inbound": {
        "segments": [
          {
            "airline": "G3",
            "airline_name": "GOL",
            "flight_no": "G37481",
            "origin": "ASU",
            "destination": "GRU",
            "origin_city": "",
            "destination_city": "",
            "departure": "2026-05-03T12:05:00",
            "arrival": "2026-05-03T14:05:00",
            "duration_seconds": 0,
            "cabin_class": "economy",
            "aircraft": ""
          },
          {
            "airline": "G3",
            "airline_name": "GOL",
            "flight_no": "G31140",
            "origin": "GRU",
            "destination": "FLN",
            "origin_city": "",
            "destination_city": "",
            "departure": "2026-05-04T09:15:00",
            "arrival": "2026-05-04T10:35:00",
            "duration_seconds": 0,
            "cabin_class": "economy",
            "aircraft": ""
          },
          {
            "airline": "G3",
            "airline_name": "GOL",
            "flight_no": "G32104",
            "origin": "FLN",
            "destination": "POA",
            "origin_city": "",
            "destination_city": "",
            "departure": "2026-05-04T21:40:00",
            "arrival": "2026-05-04T22:45:00",
            "duration_seconds": 0,
            "cabin_class": "economy",
            "aircraft": ""
          }
        ],
        "total_duration_seconds": 124800,
        "stopovers": 2
      },
      "airlines": [
        "G3"
      ],
      "owner_airline": "G3",
      "bags_price": {},
      "availability_seats": null,
      "conditions": {},
      "source": "momondo_meta",
      "source_tier": "free",
      "is_locked": false,
      "fetched_at": "2026-04-21T15:58:55.732593",
      "booking_url": "https://www.momondo.com/flight-search/POA-ASU/2026-04-30",
      "price_normalized": 430.01398
    }
  ]
}
